pymscada_process-0.0.1.dist-info/METADATA
pymscada_process-0.0.1.dist-info/WHEEL
pymscada_process-0.0.1.dist-info/licenses/LICENSE
pymscada_process/__init__.py
pymscada_process-0.0.1.dist-info/RECORD
